camera_segment/__main__.py
camera_segment/cli.py
camera_segment-0.3.3.dist-info/licenses/LICENSE
camera_segment-0.3.3.dist-info/METADATA
camera_segment-0.3.3.dist-info/WHEEL
camera_segment-0.3.3.dist-info/entry_points.txt
camera_segment-0.3.3.dist-info/top_level.txt
camera_segment-0.3.3.dist-info/RECORD
