Metadata-Version: 2.4
Name: camera-segment
Version: 0.3.3
Summary: A Python tool to capture segments of video from cameras.
Author-email: "Joshua B. Bussdieker" <jbussdieker@gmail.com>
Maintainer-email: "Joshua B. Bussdieker" <jbussdieker@gmail.com>
License-Expression: MIT
Project-URL: Homepage, https://github.com/jbussdieker/python-camera-segment
Project-URL: Documentation, https://github.com/jbussdieker/python-camera-segment/blob/main/README.md
Project-URL: Repository, https://github.com/jbussdieker/python-camera-segment
Project-URL: Issues, https://github.com/jbussdieker/python-camera-segment/issues
Project-URL: Changelog, https://github.com/jbussdieker/python-camera-segment/blob/main/CHANGELOG.md
Classifier: Topic :: Multimedia :: Video :: Capture
Classifier: Topic :: Multimedia :: Video :: Display
Classifier: Development Status :: 3 - Alpha
Classifier: Programming Language :: Python :: 3
Classifier: Programming Language :: Python :: 3.10
Classifier: Programming Language :: Python :: 3.11
Classifier: Programming Language :: Python :: 3.12
Classifier: Programming Language :: Python :: 3.13
Classifier: Operating System :: OS Independent
Classifier: Environment :: Console
Classifier: Intended Audience :: Developers
Classifier: Natural Language :: English
Classifier: Typing :: Typed
Requires-Python: >=3.10
License-File: LICENSE
Dynamic: license-file
